akshare_mcp/__init__.py
akshare_mcp/server.py
akshare_mcp_ikouhaha-0.4.0.dist-info/METADATA
akshare_mcp_ikouhaha-0.4.0.dist-info/WHEEL
akshare_mcp_ikouhaha-0.4.0.dist-info/entry_points.txt
akshare_mcp_ikouhaha-0.4.0.dist-info/licenses/LICENSE
akshare_mcp_ikouhaha-0.4.0.dist-info/RECORD
