Metadata-Version: 2.4
Name: akshare-mcp-ikouhaha
Version: 0.4.0
Summary: Simple XAUUSD Gold Data MCP Server using AkShare
Project-URL: Homepage, https://github.com/your-username/akshare-mcp
Project-URL: Repository, https://github.com/your-username/akshare-mcp
Project-URL: Issues, https://github.com/your-username/akshare-mcp/issues
Author-email: Akshare MCP Team <akshare.mcp@example.com>
License: MIT License
License-File: LICENSE
Classifier: Development Status :: 3 - Alpha
Classifier: Intended Audience :: Developers
Classifier: License :: OSI Approved :: MIT License
Classifier: Programming Language :: Python :: 3
Classifier: Programming Language :: Python :: 3.10
Classifier: Programming Language :: Python :: 3.11
Classifier: Programming Language :: Python :: 3.12
Requires-Python: >=3.10
Requires-Dist: aiosmtplib>=3.0.0
Requires-Dist: akshare>=1.12.0
Requires-Dist: mcp
Provides-Extra: dev
Requires-Dist: black>=22.0; extra == 'dev'
Requires-Dist: isort>=5.0; extra == 'dev'
Requires-Dist: mypy>=0.910; extra == 'dev'
Requires-Dist: pytest-asyncio>=0.20.0; extra == 'dev'
Requires-Dist: pytest>=6.0; extra == 'dev'
